[
    {
        "author_sc": "no",
        "cited": "10.1023/a:1013617802515",
        "oci": "061403070552-061302873626",
        "journal_sc": "no",
        "citing": "10.1007/978-3-540-72397-4_27",
        "creation": "2007",
        "timespan": "P5Y"
    },
    {
        "author_sc": "no",
        "cited": "10.1016/j.ejor.2005.11.001",
        "oci": "061403070552-0620221017",
        "journal_sc": "no",
        "citing": "10.1007/978-3-540-72397-4_27",
        "creation": "2007",
        "timespan": "P0Y"
    },
    {
        "author_sc": "no",
        "cited": "10.1007/978-1-4615-1479-4",
        "oci": "061403070552-0623067164",
        "journal_sc": "no",
        "citing": "10.1007/978-3-540-72397-4_27",
        "creation": "2007",
        "timespan": "P6Y"
    },
    {
        "author_sc": "no",
        "cited": "10.1007/0-387-25486-2_11",
        "oci": "061403070552-062603150514",
        "journal_sc": "no",
        "citing": "10.1007/978-3-540-72397-4_27",
        "creation": "2007",
        "timespan": "P2Y"
    },
    {
        "author_sc": "no",
        "cited": "10.1007/11841036_58",
        "oci": "061403070552-062603154758",
        "journal_sc": "no",
        "citing": "10.1007/978-3-540-72397-4_27",
        "creation": "2007",
        "timespan": "P1Y"
    },
    {
        "author_sc": "no",
        "cited": "10.1016/s0377-2217(02)00762-2",
        "oci": "061403070552-0670226473",
        "journal_sc": "no",
        "citing": "10.1007/978-3-540-72397-4_27",
        "creation": "2007",
        "timespan": "P3Y"
    },
    {
        "author_sc": "no",
        "cited": "10.1016/s0377-2217(98)00204-5",
        "oci": "061403070552-0680228485",
        "journal_sc": "no",
        "citing": "10.1007/978-3-540-72397-4_27",
        "creation": "2007",
        "timespan": "P8Y"
    },
    {
        "author_sc": "no",
        "cited": "10.1016/s0377-2217(99)00489-0",
        "oci": "061403070552-0680228679",
        "journal_sc": "no",
        "citing": "10.1007/978-3-540-72397-4_27",
        "creation": "2007",
        "timespan": "P6Y"
    }
]