[
    {
        "creation": "2022-08-08",
        "author_sc": "no",
        "cited": "10.1016/j.ejor.2007.12.032",
        "timespan": "P13Y3M",
        "journal_sc": "no",
        "oci": "061503443081-0610228479",
        "citing": "10.1007/s10479-022-04891-1"
    },
    {
        "creation": "2022-08-08",
        "author_sc": "no",
        "cited": "10.1016/j.ejor.2007.06.022",
        "timespan": "P13Y10M",
        "journal_sc": "no",
        "oci": "061503443081-0610228842",
        "citing": "10.1007/s10479-022-04891-1"
    },
    {
        "creation": "2022-08-08",
        "author_sc": "no",
        "cited": "10.1016/j.dam.2006.07.009",
        "timespan": "P15Y5M",
        "journal_sc": "no",
        "oci": "061503443081-0610256950",
        "citing": "10.1007/s10479-022-04891-1"
    },
    {
        "creation": "2022-08-08",
        "author_sc": "no",
        "cited": "10.1287/trsc.36.1.94.574",
        "timespan": "P20Y6M",
        "journal_sc": "no",
        "oci": "061503443081-061201612604",
        "citing": "10.1007/s10479-022-04891-1"
    },
    {
        "creation": "2022-08-08",
        "author_sc": "no",
        "cited": "10.1137/1.9781611973594",
        "timespan": "P7Y8M15D",
        "journal_sc": "no",
        "oci": "061503443081-061202648290",
        "citing": "10.1007/s10479-022-04891-1"
    },
    {
        "creation": "2022-08-08",
        "author_sc": "no",
        "cited": "10.1007/s41604-017-0002-1",
        "timespan": "P4Y10M21D",
        "journal_sc": "no",
        "oci": "061503443081-06120795379",
        "citing": "10.1007/s10479-022-04891-1"
    },
    {
        "creation": "2022-08-08",
        "author_sc": "no",
        "cited": "10.1007/3-540-45578-7_2",
        "timespan": "P21Y",
        "journal_sc": "no",
        "oci": "061503443081-061302805403",
        "citing": "10.1007/s10479-022-04891-1"
    },
    {
        "creation": "2022-08-08",
        "author_sc": "no",
        "cited": "10.1007/s12469-010-0018-5",
        "timespan": "P12Y9M",
        "journal_sc": "no",
        "oci": "061503443081-06130395689",
        "citing": "10.1007/s10479-022-04891-1"
    },
    {
        "creation": "2022-08-08",
        "author_sc": "yes",
        "cited": "10.1016/j.cor.2019.104777",
        "timespan": "P2Y7M",
        "journal_sc": "no",
        "oci": "061503443081-06140165512",
        "citing": "10.1007/s10479-022-04891-1"
    },
    {
        "creation": "2022-08-08",
        "author_sc": "no",
        "cited": "10.1137/0110015",
        "timespan": "P60Y5M",
        "journal_sc": "no",
        "oci": "061503443081-061402363961",
        "citing": "10.1007/s10479-022-04891-1"
    },
    {
        "creation": "2022-08-08",
        "author_sc": "no",
        "cited": "10.1109/gol.2016.7731723",
        "timespan": "P6Y3M",
        "journal_sc": "no",
        "oci": "061503443081-061402459721",
        "citing": "10.1007/s10479-022-04891-1"
    },
    {
        "creation": "2022-08-08",
        "author_sc": "no",
        "cited": "10.1016/j.cor.2014.09.007",
        "timespan": "P7Y6M",
        "journal_sc": "no",
        "oci": "061503443081-06150167502",
        "citing": "10.1007/s10479-022-04891-1"
    },
    {
        "creation": "2022-08-08",
        "author_sc": "no",
        "cited": "10.1111/j.1540-5915.1983.tb00172.x",
        "timespan": "P39Y7M",
        "journal_sc": "no",
        "oci": "061503443081-061502173203",
        "citing": "10.1007/s10479-022-04891-1"
    },
    {
        "creation": "2022-08-08",
        "author_sc": "no",
        "cited": "10.1016/s0167-5060(08)70356-x",
        "timespan": "P43Y",
        "journal_sc": "no",
        "oci": "061503443081-061503246593",
        "citing": "10.1007/s10479-022-04891-1"
    },
    {
        "creation": "2022-08-08",
        "author_sc": "no",
        "cited": "10.1016/s0377-2217(96)00188-9",
        "timespan": "P24Y11M",
        "journal_sc": "no",
        "oci": "061503443081-06160225303",
        "citing": "10.1007/s10479-022-04891-1"
    },
    {
        "creation": "2022-08-08",
        "author_sc": "no",
        "cited": "10.1016/j.cor.2005.07.012",
        "timespan": "P15Y2M",
        "journal_sc": "no",
        "oci": "061503443081-06170167774",
        "citing": "10.1007/s10479-022-04891-1"
    },
    {
        "creation": "2022-08-08",
        "author_sc": "no",
        "cited": "10.1016/j.trb.2015.06.002",
        "timespan": "P6Y11M",
        "journal_sc": "no",
        "oci": "061503443081-06170398659",
        "citing": "10.1007/s10479-022-04891-1"
    },
    {
        "creation": "2022-08-08",
        "author_sc": "no",
        "cited": "10.1016/j.ejor.2020.10.037",
        "timespan": "P1Y1M",
        "journal_sc": "no",
        "oci": "061503443081-06180224538",
        "citing": "10.1007/s10479-022-04891-1"
    },
    {
        "creation": "2022-08-08",
        "author_sc": "no",
        "cited": "10.1016/j.tre.2017.07.004",
        "timespan": "P4Y3M",
        "journal_sc": "no",
        "oci": "061503443081-06180830095",
        "citing": "10.1007/s10479-022-04891-1"
    },
    {
        "creation": "2022-08-08",
        "author_sc": "no",
        "cited": "10.1287/opre.35.2.254",
        "timespan": "P35Y4M",
        "journal_sc": "no",
        "oci": "061503443081-06190753118",
        "citing": "10.1007/s10479-022-04891-1"
    },
    {
        "creation": "2022-08-08",
        "author_sc": "no",
        "cited": "10.1016/j.tre.2009.08.012",
        "timespan": "P12Y3M",
        "journal_sc": "no",
        "oci": "061503443081-06190835523",
        "citing": "10.1007/s10479-022-04891-1"
    },
    {
        "creation": "2022-08-08",
        "author_sc": "no",
        "cited": "10.1007/bf01386316",
        "timespan": "P59Y8M",
        "journal_sc": "no",
        "oci": "061503443081-06202219821",
        "citing": "10.1007/s10479-022-04891-1"
    },
    {
        "creation": "2022-08-08",
        "author_sc": "no",
        "cited": "10.1007/s43069-020-00023-2",
        "timespan": "P1Y11M",
        "journal_sc": "no",
        "oci": "061503443081-06202278921",
        "citing": "10.1007/s10479-022-04891-1"
    },
    {
        "creation": "2022-08-08",
        "author_sc": "no",
        "cited": "10.1016/j.ejor.2016.12.005",
        "timespan": "P5Y2M",
        "journal_sc": "no",
        "oci": "061503443081-06210225649",
        "citing": "10.1007/s10479-022-04891-1"
    },
    {
        "creation": "2022-08-08",
        "author_sc": "yes",
        "cited": "10.1007/s10951-019-00620-y",
        "timespan": "P2Y11M2D",
        "journal_sc": "no",
        "oci": "061503443081-062103120373",
        "citing": "10.1007/s10479-022-04891-1"
    },
    {
        "creation": "2022-08-08",
        "author_sc": "no",
        "cited": "10.1007/s10951-016-0482-0",
        "timespan": "P6Y3M17D",
        "journal_sc": "no",
        "oci": "061503443081-062103120507",
        "citing": "10.1007/s10479-022-04891-1"
    },
    {
        "creation": "2022-08-08",
        "author_sc": "no",
        "cited": "10.1007/s10951-010-0222-9",
        "timespan": "P11Y7M1D",
        "journal_sc": "no",
        "oci": "061503443081-062103120752",
        "citing": "10.1007/s10479-022-04891-1"
    },
    {
        "creation": "2022-08-08",
        "author_sc": "no",
        "cited": "10.1007/s10951-008-0079-3",
        "timespan": "P13Y11M5D",
        "journal_sc": "no",
        "oci": "061503443081-062103120879",
        "citing": "10.1007/s10479-022-04891-1"
    },
    {
        "creation": "2022-08-08",
        "author_sc": "no",
        "cited": "10.1287/opre.1060.0371",
        "timespan": "P15Y2M",
        "journal_sc": "no",
        "oci": "061503443081-06210748627",
        "citing": "10.1007/s10479-022-04891-1"
    },
    {
        "creation": "2022-08-08",
        "author_sc": "no",
        "cited": "10.1287/opre.1060.0286",
        "timespan": "P16Y0M",
        "journal_sc": "no",
        "oci": "061503443081-06210748704",
        "citing": "10.1007/s10479-022-04891-1"
    },
    {
        "creation": "2022-08-08",
        "author_sc": "no",
        "cited": "10.1016/j.cie.2008.09.037",
        "timespan": "P13Y4M",
        "journal_sc": "no",
        "oci": "061503443081-062201291508",
        "citing": "10.1007/s10479-022-04891-1"
    },
    {
        "creation": "2022-08-08",
        "author_sc": "no",
        "cited": "10.1002/net.3230110204",
        "timespan": "P41Y",
        "journal_sc": "no",
        "oci": "061503443081-06220438748",
        "citing": "10.1007/s10479-022-04891-1"
    },
    {
        "creation": "2022-08-08",
        "author_sc": "no",
        "cited": "10.1504/ijor.2019.096942",
        "timespan": "P3Y",
        "journal_sc": "no",
        "oci": "061503443081-062301362426",
        "citing": "10.1007/s10479-022-04891-1"
    },
    {
        "creation": "2022-08-08",
        "author_sc": "no",
        "cited": "10.1007/s10479-012-1237-8",
        "timespan": "P9Y8M22D",
        "journal_sc": "yes",
        "oci": "061503443081-062301987479",
        "citing": "10.1007/s10479-022-04891-1"
    },
    {
        "creation": "2022-08-08",
        "author_sc": "no",
        "cited": "10.1007/s10479-011-1050-9",
        "timespan": "P10Y7M2D",
        "journal_sc": "yes",
        "oci": "061503443081-062301987689",
        "citing": "10.1007/s10479-022-04891-1"
    },
    {
        "creation": "2022-08-08",
        "author_sc": "yes",
        "cited": "10.1016/j.ejor.2014.09.065",
        "timespan": "P7Y4M",
        "journal_sc": "no",
        "oci": "061503443081-06230228826",
        "citing": "10.1007/s10479-022-04891-1"
    },
    {
        "creation": "2022-08-08",
        "author_sc": "no",
        "cited": "10.1002/9781118033036",
        "timespan": "P22Y2M23D",
        "journal_sc": "no",
        "oci": "061503443081-0623066838",
        "citing": "10.1007/s10479-022-04891-1"
    },
    {
        "creation": "2022-08-08",
        "author_sc": "no",
        "cited": "10.1007/s00170-005-2585-1",
        "timespan": "P16Y6M21D",
        "journal_sc": "no",
        "oci": "061503443081-06240795438",
        "citing": "10.1007/s10479-022-04891-1"
    },
    {
        "creation": "2022-08-08",
        "author_sc": "no",
        "cited": "10.1016/j.ejor.2011.06.013",
        "timespan": "P10Y8M",
        "journal_sc": "no",
        "oci": "061503443081-06250221174",
        "citing": "10.1007/s10479-022-04891-1"
    },
    {
        "creation": "2022-08-08",
        "author_sc": "no",
        "cited": "10.1007/s10107-003-0375-9",
        "timespan": "P19Y4M",
        "journal_sc": "no",
        "oci": "061503443081-0630230615",
        "citing": "10.1007/s10479-022-04891-1"
    },
    {
        "creation": "2022-08-08",
        "author_sc": "no",
        "cited": "10.1007/978-3-642-04244-7_33",
        "timespan": "P13Y",
        "journal_sc": "no",
        "oci": "061503443081-06303507592",
        "citing": "10.1007/s10479-022-04891-1"
    },
    {
        "creation": "2022-08-08",
        "author_sc": "yes",
        "cited": "10.1080/00207543.2018.1470696",
        "timespan": "P4Y2M22D",
        "journal_sc": "no",
        "oci": "061503443081-0630409627",
        "citing": "10.1007/s10479-022-04891-1"
    },
    {
        "creation": "2022-08-08",
        "author_sc": "no",
        "cited": "10.1007/978-3-319-26580-3",
        "timespan": "P6Y",
        "journal_sc": "no",
        "oci": "061503443081-063050993",
        "citing": "10.1007/s10479-022-04891-1"
    },
    {
        "creation": "2022-08-08",
        "author_sc": "no",
        "cited": "10.1016/j.jfoodeng.2006.05.029",
        "timespan": "P15Y3M",
        "journal_sc": "no",
        "oci": "061503443081-0635043247",
        "citing": "10.1007/s10479-022-04891-1"
    },
    {
        "creation": "2022-08-08",
        "author_sc": "no",
        "cited": "10.1016/s1478-4092(03)00003-7",
        "timespan": "P19Y5M",
        "journal_sc": "no",
        "oci": "061503443081-06501456007",
        "citing": "10.1007/s10479-022-04891-1"
    },
    {
        "creation": "2022-08-08",
        "author_sc": "no",
        "cited": "10.1016/s0925-5273(98)00250-3",
        "timespan": "P22Y11M",
        "journal_sc": "no",
        "oci": "061503443081-0660843489",
        "citing": "10.1007/s10479-022-04891-1"
    },
    {
        "creation": "2022-08-08",
        "author_sc": "no",
        "cited": "10.1007/s00453-015-0082-y",
        "timespan": "P6Y9M13D",
        "journal_sc": "no",
        "oci": "061503443081-06703230569",
        "citing": "10.1007/s10479-022-04891-1"
    },
    {
        "creation": "2022-08-08",
        "author_sc": "no",
        "cited": "10.1016/s0167-5060(08)70743-x",
        "timespan": "P45Y",
        "journal_sc": "no",
        "oci": "061503443081-06703640353",
        "citing": "10.1007/s10479-022-04891-1"
    },
    {
        "creation": "2022-08-08",
        "author_sc": "no",
        "cited": "10.1016/s0377-2217(99)00153-8",
        "timespan": "P22Y7M",
        "journal_sc": "no",
        "oci": "061503443081-0680228583",
        "citing": "10.1007/s10479-022-04891-1"
    },
    {
        "creation": "2022-08-08",
        "author_sc": "no",
        "cited": "10.1287/mnsc.36.2.240",
        "timespan": "P32Y6M",
        "journal_sc": "no",
        "oci": "061503443081-06802350655",
        "citing": "10.1007/s10479-022-04891-1"
    },
    {
        "creation": "2022-08-08",
        "author_sc": "no",
        "cited": "10.1287/mnsc.19.5.544",
        "timespan": "P49Y7M",
        "journal_sc": "no",
        "oci": "061503443081-06802350656",
        "citing": "10.1007/s10479-022-04891-1"
    },
    {
        "creation": "2022-08-08",
        "author_sc": "no",
        "cited": "10.1287/ijoc.1100.0446",
        "timespan": "P10Y3M",
        "journal_sc": "no",
        "oci": "061503443081-0680834515",
        "citing": "10.1007/s10479-022-04891-1"
    }
]