[
    {
        "creation": "2018-03-06",
        "author_sc": "no",
        "cited": "10.1016/s0305-0483(00)00046-3",
        "timespan": "P16Y9M",
        "journal_sc": "no",
        "oci": "0640285809-0610170819",
        "citing": "10.1111/mice.12356"
    },
    {
        "creation": "2018-03-06",
        "author_sc": "no",
        "cited": "10.1061/(asce)0733-9364(2001)127:1(28)",
        "timespan": "P17Y1M",
        "journal_sc": "no",
        "oci": "0640285809-061601436710",
        "citing": "10.1111/mice.12356"
    },
    {
        "creation": "2018-03-06",
        "author_sc": "no",
        "cited": "10.1061/(asce)0733-9364(1997)123:4(450)",
        "timespan": "P20Y3M",
        "journal_sc": "no",
        "oci": "0640285809-061601436822",
        "citing": "10.1111/mice.12356"
    },
    {
        "creation": "2018-03-06",
        "author_sc": "no",
        "cited": "10.1061/(asce)0733-9364(2001)127:4(270)",
        "timespan": "P16Y7M",
        "journal_sc": "no",
        "oci": "0640285809-061601436825",
        "citing": "10.1111/mice.12356"
    },
    {
        "creation": "2018-03-06",
        "author_sc": "no",
        "cited": "10.1061/(asce)0733-9364(2001)127:1(18)",
        "timespan": "P17Y1M",
        "journal_sc": "no",
        "oci": "0640285809-061601436927",
        "citing": "10.1111/mice.12356"
    },
    {
        "creation": "2018-03-06",
        "author_sc": "no",
        "cited": "10.1016/s0377-2217(98)00272-0",
        "timespan": "P18Y6M",
        "journal_sc": "no",
        "oci": "0640285809-06160225301",
        "citing": "10.1111/mice.12356"
    },
    {
        "creation": "2018-03-06",
        "author_sc": "no",
        "cited": "10.1057/jors.2012.164",
        "timespan": "P4Y7M",
        "journal_sc": "no",
        "oci": "0640285809-061702182888",
        "citing": "10.1111/mice.12356"
    },
    {
        "creation": "2018-03-06",
        "author_sc": "no",
        "cited": "10.1016/j.proeng.2015.10.107",
        "timespan": "P3Y",
        "journal_sc": "no",
        "oci": "0640285809-061702640016",
        "citing": "10.1111/mice.12356"
    },
    {
        "creation": "2018-03-06",
        "author_sc": "no",
        "cited": "10.1108/01443579310046454",
        "timespan": "P24Y4M5D",
        "journal_sc": "no",
        "oci": "0640285809-061703059033",
        "citing": "10.1111/mice.12356"
    },
    {
        "creation": "2018-03-06",
        "author_sc": "no",
        "cited": "10.1061/(asce)co.1943-7862.0000097",
        "timespan": "P8Y4M",
        "journal_sc": "no",
        "oci": "0640285809-061801429669",
        "citing": "10.1111/mice.12356"
    },
    {
        "creation": "2018-03-06",
        "author_sc": "no",
        "cited": "10.1061/(asce)0733-9364(1988)114:1(36)",
        "timespan": "P30Y0M",
        "journal_sc": "no",
        "oci": "0640285809-061801429877",
        "citing": "10.1111/mice.12356"
    },
    {
        "creation": "2018-03-06",
        "author_sc": "no",
        "cited": "10.1007/978-3-319-05443-8_17",
        "timespan": "P3Y4M26D",
        "journal_sc": "no",
        "oci": "0640285809-061802617774",
        "citing": "10.1111/mice.12356"
    },
    {
        "creation": "2018-03-06",
        "author_sc": "yes",
        "cited": "10.1016/j.autcon.2017.01.018",
        "timespan": "P0Y10M",
        "journal_sc": "no",
        "oci": "0640285809-061803066790",
        "citing": "10.1111/mice.12356"
    },
    {
        "creation": "2018-03-06",
        "author_sc": "no",
        "cited": "10.1016/j.autcon.2016.05.011",
        "timespan": "P1Y5M",
        "journal_sc": "no",
        "oci": "0640285809-061803066922",
        "citing": "10.1111/mice.12356"
    },
    {
        "creation": "2018-03-06",
        "author_sc": "no",
        "cited": "10.1016/j.autcon.2012.11.002",
        "timespan": "P4Y10M",
        "journal_sc": "no",
        "oci": "0640285809-061803067466",
        "citing": "10.1111/mice.12356"
    },
    {
        "creation": "2018-03-06",
        "author_sc": "no",
        "cited": "10.1061/(asce)0733-9364(2008)134:4(253)",
        "timespan": "P9Y11M",
        "journal_sc": "no",
        "oci": "0640285809-061901433190",
        "citing": "10.1111/mice.12356"
    },
    {
        "creation": "2018-03-06",
        "author_sc": "no",
        "cited": "10.1061/(asce)0733-9364(1990)116:2(331)",
        "timespan": "P27Y9M",
        "journal_sc": "no",
        "oci": "0640285809-061901433296",
        "citing": "10.1111/mice.12356"
    },
    {
        "creation": "2018-03-06",
        "author_sc": "no",
        "cited": "10.1061/(asce)0733-9364(2006)132:1(26)",
        "timespan": "P12Y2M",
        "journal_sc": "no",
        "oci": "0640285809-061901433746",
        "citing": "10.1111/mice.12356"
    },
    {
        "creation": "2018-03-06",
        "author_sc": "no",
        "cited": "10.1016/s0305-0548(97)00055-5",
        "timespan": "P19Y11M",
        "journal_sc": "no",
        "oci": "0640285809-06190174478",
        "citing": "10.1111/mice.12356"
    },
    {
        "creation": "2018-03-06",
        "author_sc": "yes",
        "cited": "10.1016/j.autcon.2012.10.003",
        "timespan": "P5Y2M",
        "journal_sc": "no",
        "oci": "0640285809-061903078905",
        "citing": "10.1111/mice.12356"
    },
    {
        "creation": "2018-03-06",
        "author_sc": "no",
        "cited": "10.1016/j.autcon.2011.12.009",
        "timespan": "P5Y8M",
        "journal_sc": "no",
        "oci": "0640285809-061903078997",
        "citing": "10.1111/mice.12356"
    },
    {
        "creation": "2018-03-06",
        "author_sc": "no",
        "cited": "10.1016/j.autcon.2009.04.006",
        "timespan": "P8Y4M",
        "journal_sc": "no",
        "oci": "0640285809-061903079328",
        "citing": "10.1111/mice.12356"
    },
    {
        "creation": "2018-03-06",
        "author_sc": "no",
        "cited": "10.3233/fi-2009-157",
        "timespan": "P9Y",
        "journal_sc": "no",
        "oci": "0640285809-06203725403",
        "citing": "10.1111/mice.12356"
    },
    {
        "creation": "2018-03-06",
        "author_sc": "no",
        "cited": "10.1515/ace-2017-0001",
        "timespan": "P0Y11M6D",
        "journal_sc": "no",
        "oci": "0640285809-062101900712",
        "citing": "10.1111/mice.12356"
    },
    {
        "creation": "2018-03-06",
        "author_sc": "no",
        "cited": "10.1080/01446193.2015.1100317",
        "timespan": "P2Y6M4D",
        "journal_sc": "no",
        "oci": "0640285809-06220157477",
        "citing": "10.1111/mice.12356"
    },
    {
        "creation": "2018-03-06",
        "author_sc": "no",
        "cited": "10.1080/01446190903369907",
        "timespan": "P8Y1M",
        "journal_sc": "no",
        "oci": "0640285809-06230166396",
        "citing": "10.1111/mice.12356"
    },
    {
        "creation": "2018-03-06",
        "author_sc": "no",
        "cited": "10.1080/07408179508936773",
        "timespan": "P22Y5M",
        "journal_sc": "no",
        "oci": "0640285809-062501200767",
        "citing": "10.1111/mice.12356"
    },
    {
        "creation": "2018-03-06",
        "author_sc": "no",
        "cited": "10.1061/(asce)0733-9364(2002)128:6(545)",
        "timespan": "P15Y3M",
        "journal_sc": "no",
        "oci": "0640285809-062601454606",
        "citing": "10.1111/mice.12356"
    },
    {
        "creation": "2018-03-06",
        "author_sc": "no",
        "cited": "10.1016/j.ejor.2004.04.002",
        "timespan": "P12Y6M",
        "journal_sc": "no",
        "oci": "0640285809-0630222039",
        "citing": "10.1111/mice.12356"
    },
    {
        "creation": "2018-03-06",
        "author_sc": "no",
        "cited": "10.1111/mice.12277",
        "timespan": "P0Y7M2D",
        "journal_sc": "yes",
        "oci": "0640285809-0640285856",
        "citing": "10.1111/mice.12356"
    },
    {
        "creation": "2018-03-06",
        "author_sc": "yes",
        "cited": "10.1111/mice.12233",
        "timespan": "P1Y3M25D",
        "journal_sc": "yes",
        "oci": "0640285809-0640285904",
        "citing": "10.1111/mice.12356"
    },
    {
        "creation": "2018-03-06",
        "author_sc": "yes",
        "cited": "10.1111/mice.12166",
        "timespan": "P2Y6M14D",
        "journal_sc": "yes",
        "oci": "0640285809-0640285998",
        "citing": "10.1111/mice.12356"
    },
    {
        "creation": "2018-03-06",
        "author_sc": "no",
        "cited": "10.3130/jaabe.4.461",
        "timespan": "P12Y4M",
        "journal_sc": "no",
        "oci": "0640285809-0648016587",
        "citing": "10.1111/mice.12356"
    },
    {
        "creation": "2018-03-06",
        "author_sc": "no",
        "cited": "10.1287/mnsc.16.1.93",
        "timespan": "P48Y6M",
        "journal_sc": "no",
        "oci": "0640285809-06602354759",
        "citing": "10.1111/mice.12356"
    },
    {
        "creation": "2018-03-06",
        "author_sc": "no",
        "cited": "10.1061/jcceaz.0000877",
        "timespan": "P37Y9M",
        "journal_sc": "no",
        "oci": "0640285809-06901254871",
        "citing": "10.1111/mice.12356"
    },
    {
        "creation": "2018-03-06",
        "author_sc": "no",
        "cited": "10.1007/978-3-540-24800-2",
        "timespan": "P15Y",
        "journal_sc": "no",
        "oci": "0640285809-069063051",
        "citing": "10.1111/mice.12356"
    }
]