[
    {
        "creation": "1998-04",
        "author_sc": "no",
        "cited": "10.1007/bf00123686",
        "timespan": "P3Y0M",
        "journal_sc": "no",
        "oci": "06190174478-0610874918",
        "citing": "10.1016/s0305-0548(97)00055-5"
    },
    {
        "creation": "1998-04",
        "author_sc": "no",
        "cited": "10.1080/00207549608905015",
        "timespan": "P1Y8M",
        "journal_sc": "no",
        "oci": "06190174478-06120404658",
        "citing": "10.1016/s0305-0548(97)00055-5"
    },
    {
        "creation": "1998-04",
        "author_sc": "no",
        "cited": "10.1016/0305-0548(95)00074-7",
        "timespan": "P1Y8M",
        "journal_sc": "yes",
        "oci": "06190174478-06130167554",
        "citing": "10.1016/s0305-0548(97)00055-5"
    },
    {
        "creation": "1998-04",
        "author_sc": "no",
        "cited": "10.1007/bf01545587",
        "timespan": "P0Y7M",
        "journal_sc": "no",
        "oci": "06190174478-06150195118",
        "citing": "10.1016/s0305-0548(97)00055-5"
    },
    {
        "creation": "1998-04",
        "author_sc": "no",
        "cited": "10.1016/s0377-2217(97)00335-4",
        "timespan": "-P0Y2M",
        "journal_sc": "no",
        "oci": "06190174478-06160224816",
        "citing": "10.1016/s0305-0548(97)00055-5"
    },
    {
        "creation": "1998-04",
        "author_sc": "no",
        "cited": "10.1016/s0377-2217(97)00348-2",
        "timespan": "-P0Y2M",
        "journal_sc": "no",
        "oci": "06190174478-06160225114",
        "citing": "10.1016/s0305-0548(97)00055-5"
    },
    {
        "creation": "1998-04",
        "author_sc": "no",
        "cited": "10.1002/1520-6750(199002)37:1<61::aid-nav3220370104>3.0.co;2-s",
        "timespan": "P8Y2M",
        "journal_sc": "no",
        "oci": "06190174478-061602458818",
        "citing": "10.1016/s0305-0548(97)00055-5"
    },
    {
        "creation": "1998-04",
        "author_sc": "no",
        "cited": "10.1287/opre.16.3.559",
        "timespan": "P29Y10M",
        "journal_sc": "no",
        "oci": "06190174478-06160752962",
        "citing": "10.1016/s0305-0548(97)00055-5"
    },
    {
        "creation": "1998-04",
        "author_sc": "no",
        "cited": "10.1108/01443579310046454",
        "timespan": "P4Y5M",
        "journal_sc": "no",
        "oci": "06190174478-061703059033",
        "citing": "10.1016/s0305-0548(97)00055-5"
    },
    {
        "creation": "1998-04",
        "author_sc": "no",
        "cited": "10.1287/opre.45.2.201",
        "timespan": "P1Y0M",
        "journal_sc": "no",
        "oci": "06190174478-06170754577",
        "citing": "10.1016/s0305-0548(97)00055-5"
    },
    {
        "creation": "1998-04",
        "author_sc": "no",
        "cited": "10.1057/jors.1972.48",
        "timespan": "P25Y7M",
        "journal_sc": "no",
        "oci": "06190174478-061902175902",
        "citing": "10.1016/s0305-0548(97)00055-5"
    },
    {
        "creation": "1998-04",
        "author_sc": "no",
        "cited": "10.1016/0167-6377(94)90064-7",
        "timespan": "P3Y7M",
        "journal_sc": "no",
        "oci": "06190174478-06190457992",
        "citing": "10.1016/s0305-0548(97)00055-5"
    },
    {
        "creation": "1998-04",
        "author_sc": "no",
        "cited": "10.1287/opre.7.5.621",
        "timespan": "P38Y6M",
        "journal_sc": "no",
        "oci": "06190174478-06190753094",
        "citing": "10.1016/s0305-0548(97)00055-5"
    },
    {
        "creation": "1998-04",
        "author_sc": "no",
        "cited": "10.1287/opre.12.3.395",
        "timespan": "P33Y10M",
        "journal_sc": "no",
        "oci": "06190174478-06190753174",
        "citing": "10.1016/s0305-0548(97)00055-5"
    },
    {
        "creation": "1998-04",
        "author_sc": "no",
        "cited": "10.1287/opre.18.2.263",
        "timespan": "P28Y0M",
        "journal_sc": "no",
        "oci": "06190174478-06190753607",
        "citing": "10.1016/s0305-0548(97)00055-5"
    },
    {
        "creation": "1998-04",
        "author_sc": "no",
        "cited": "10.1287/opre.30.2.375",
        "timespan": "P16Y0M",
        "journal_sc": "no",
        "oci": "06190174478-06210747984",
        "citing": "10.1016/s0305-0548(97)00055-5"
    },
    {
        "creation": "1998-04",
        "author_sc": "no",
        "cited": "10.1057/jors.1966.72",
        "timespan": "P31Y4M",
        "journal_sc": "no",
        "oci": "06190174478-062202162148",
        "citing": "10.1016/s0305-0548(97)00055-5"
    },
    {
        "creation": "1998-04",
        "author_sc": "no",
        "cited": "10.1007/bf02283745",
        "timespan": "P9Y4M",
        "journal_sc": "no",
        "oci": "06190174478-062401979266",
        "citing": "10.1016/s0305-0548(97)00055-5"
    },
    {
        "creation": "1998-04",
        "author_sc": "no",
        "cited": "10.1080/07408178508975272",
        "timespan": "P13Y1M",
        "journal_sc": "no",
        "oci": "06190174478-062501200517",
        "citing": "10.1016/s0305-0548(97)00055-5"
    },
    {
        "creation": "1998-04",
        "author_sc": "no",
        "cited": "10.1080/07408179508936773",
        "timespan": "P2Y6M",
        "journal_sc": "no",
        "oci": "06190174478-062501200767",
        "citing": "10.1016/s0305-0548(97)00055-5"
    },
    {
        "creation": "1998-04",
        "author_sc": "no",
        "cited": "10.1007/bf02022042",
        "timespan": "P12Y4M",
        "journal_sc": "no",
        "oci": "06190174478-062501984264",
        "citing": "10.1016/s0305-0548(97)00055-5"
    },
    {
        "creation": "1998-04",
        "author_sc": "no",
        "cited": "10.1002/nav.3800230110",
        "timespan": "P22Y1M",
        "journal_sc": "no",
        "oci": "06190174478-062602213844",
        "citing": "10.1016/s0305-0548(97)00055-5"
    },
    {
        "creation": "1998-04",
        "author_sc": "no",
        "cited": "10.1002/nav.3800190110",
        "timespan": "P26Y1M",
        "journal_sc": "no",
        "oci": "06190174478-062602213915",
        "citing": "10.1016/s0305-0548(97)00055-5"
    },
    {
        "creation": "1998-04",
        "author_sc": "no",
        "cited": "10.1016/s0305-0548(97)00043-9",
        "timespan": "",
        "journal_sc": "no",
        "oci": "06190174478-062603616431",
        "citing": "10.1016/s0305-0548(97)00055-5"
    },
    {
        "creation": "1998-04",
        "author_sc": "no",
        "cited": "10.1016/0166-218x(83)90012-4",
        "timespan": "P15Y3M",
        "journal_sc": "no",
        "oci": "06190174478-0630249703",
        "citing": "10.1016/s0305-0548(97)00055-5"
    },
    {
        "creation": "1998-04",
        "author_sc": "no",
        "cited": "10.1016/0377-2217(87)90240-2",
        "timespan": "P10Y10M",
        "journal_sc": "no",
        "oci": "06190174478-0640227983",
        "citing": "10.1016/s0305-0548(97)00055-5"
    },
    {
        "creation": "1998-04",
        "author_sc": "no",
        "cited": "10.1287/mnsc.28.10.1197",
        "timespan": "P15Y6M",
        "journal_sc": "no",
        "oci": "06190174478-06402364816",
        "citing": "10.1016/s0305-0548(97)00055-5"
    },
    {
        "creation": "1998-04",
        "author_sc": "no",
        "cited": "10.1287/mnsc.42.10.1395",
        "timespan": "P1Y6M",
        "journal_sc": "no",
        "oci": "06190174478-06402365307",
        "citing": "10.1016/s0305-0548(97)00055-5"
    },
    {
        "creation": "1998-04",
        "author_sc": "no",
        "cited": "10.1016/0377-2217(93)90185-p",
        "timespan": "P5Y3M",
        "journal_sc": "no",
        "oci": "06190174478-0650223124",
        "citing": "10.1016/s0305-0548(97)00055-5"
    },
    {
        "creation": "1998-04",
        "author_sc": "no",
        "cited": "10.1016/0377-2217(90)90121-q",
        "timespan": "P7Y5M",
        "journal_sc": "no",
        "oci": "06190174478-0650223407",
        "citing": "10.1016/s0305-0548(97)00055-5"
    },
    {
        "creation": "1998-04",
        "author_sc": "no",
        "cited": "10.1016/0377-2217(90)90118-u",
        "timespan": "P7Y5M",
        "journal_sc": "no",
        "oci": "06190174478-0650223482",
        "citing": "10.1016/s0305-0548(97)00055-5"
    },
    {
        "creation": "1998-04",
        "author_sc": "no",
        "cited": "10.1016/0377-2217(94)90016-7",
        "timespan": "P3Y9M",
        "journal_sc": "no",
        "oci": "06190174478-0650223737",
        "citing": "10.1016/s0305-0548(97)00055-5"
    },
    {
        "creation": "1998-04",
        "author_sc": "no",
        "cited": "10.1016/0377-2217(80)90053-3",
        "timespan": "P17Y6M",
        "journal_sc": "no",
        "oci": "06190174478-0650223900",
        "citing": "10.1016/s0305-0548(97)00055-5"
    },
    {
        "creation": "1998-04",
        "author_sc": "no",
        "cited": "10.1016/0377-2217(91)90150-t",
        "timespan": "P7Y1M",
        "journal_sc": "no",
        "oci": "06190174478-0650223914",
        "citing": "10.1016/s0305-0548(97)00055-5"
    },
    {
        "creation": "1998-04",
        "author_sc": "no",
        "cited": "10.1287/mnsc.24.11.1163",
        "timespan": "P19Y9M",
        "journal_sc": "no",
        "oci": "06190174478-06502358219",
        "citing": "10.1016/s0305-0548(97)00055-5"
    },
    {
        "creation": "1998-04",
        "author_sc": "no",
        "cited": "10.1287/mnsc.16.11.728",
        "timespan": "P27Y9M",
        "journal_sc": "no",
        "oci": "06190174478-06502358221",
        "citing": "10.1016/s0305-0548(97)00055-5"
    },
    {
        "creation": "1998-04",
        "author_sc": "no",
        "cited": "10.1287/mnsc.44.5.714",
        "timespan": "-P0Y1M",
        "journal_sc": "no",
        "oci": "06190174478-06502358222",
        "citing": "10.1016/s0305-0548(97)00055-5"
    },
    {
        "creation": "1998-04",
        "author_sc": "no",
        "cited": "10.1287/mnsc.30.7.854",
        "timespan": "P13Y9M",
        "journal_sc": "no",
        "oci": "06190174478-06502359105",
        "citing": "10.1016/s0305-0548(97)00055-5"
    },
    {
        "creation": "1998-04",
        "author_sc": "no",
        "cited": "10.1016/0377-2217(94)90018-3",
        "timespan": "P3Y9M",
        "journal_sc": "no",
        "oci": "06190174478-0660225387",
        "citing": "10.1016/s0305-0548(97)00055-5"
    },
    {
        "creation": "1998-04",
        "author_sc": "no",
        "cited": "10.1016/0377-2217(93)90176-n",
        "timespan": "P5Y3M",
        "journal_sc": "no",
        "oci": "06190174478-0660225804",
        "citing": "10.1016/s0305-0548(97)00055-5"
    },
    {
        "creation": "1998-04",
        "author_sc": "no",
        "cited": "10.1016/0377-2217(93)90340-s",
        "timespan": "P5Y1M",
        "journal_sc": "no",
        "oci": "06190174478-0660225822",
        "citing": "10.1016/s0305-0548(97)00055-5"
    },
    {
        "creation": "1998-04",
        "author_sc": "no",
        "cited": "10.1287/mnsc.16.1.93",
        "timespan": "P28Y7M",
        "journal_sc": "no",
        "oci": "06190174478-06602354759",
        "citing": "10.1016/s0305-0548(97)00055-5"
    },
    {
        "creation": "1998-04",
        "author_sc": "no",
        "cited": "10.1287/mnsc.22.11.1186",
        "timespan": "P21Y9M",
        "journal_sc": "no",
        "oci": "06190174478-06602355455",
        "citing": "10.1016/s0305-0548(97)00055-5"
    },
    {
        "creation": "1998-04",
        "author_sc": "no",
        "cited": "10.1287/mnsc.43.11.1485",
        "timespan": "P0Y5M",
        "journal_sc": "no",
        "oci": "06190174478-06602355467",
        "citing": "10.1016/s0305-0548(97)00055-5"
    },
    {
        "creation": "1998-04",
        "author_sc": "no",
        "cited": "10.1287/mnsc.20.6.990",
        "timespan": "P24Y2M",
        "journal_sc": "no",
        "oci": "06190174478-06602355468",
        "citing": "10.1016/s0305-0548(97)00055-5"
    },
    {
        "creation": "1998-04",
        "author_sc": "no",
        "cited": "10.1080/05695557608975107",
        "timespan": "P21Y4M",
        "journal_sc": "no",
        "oci": "06190174478-06701238168",
        "citing": "10.1016/s0305-0548(97)00055-5"
    },
    {
        "creation": "1998-04",
        "author_sc": "no",
        "cited": "10.1080/05695557808975212",
        "timespan": "P19Y7M",
        "journal_sc": "no",
        "oci": "06190174478-06701238302",
        "citing": "10.1016/s0305-0548(97)00055-5"
    },
    {
        "creation": "1998-04",
        "author_sc": "no",
        "cited": "10.1080/05695557308974922",
        "timespan": "P24Y4M",
        "journal_sc": "no",
        "oci": "06190174478-06701238571",
        "citing": "10.1016/s0305-0548(97)00055-5"
    },
    {
        "creation": "1998-04",
        "author_sc": "no",
        "cited": "10.1080/05695557308974916",
        "timespan": "P24Y4M",
        "journal_sc": "no",
        "oci": "06190174478-06701238621",
        "citing": "10.1016/s0305-0548(97)00055-5"
    },
    {
        "creation": "1998-04",
        "author_sc": "yes",
        "cited": "10.1016/0377-2217(94)00344-0",
        "timespan": "P1Y10M",
        "journal_sc": "no",
        "oci": "06190174478-0670226777",
        "citing": "10.1016/s0305-0548(97)00055-5"
    },
    {
        "creation": "1998-04",
        "author_sc": "no",
        "cited": "10.1016/0377-2217(94)00184-e",
        "timespan": "P2Y11M",
        "journal_sc": "no",
        "oci": "06190174478-0670226783",
        "citing": "10.1016/s0305-0548(97)00055-5"
    },
    {
        "creation": "1998-04",
        "author_sc": "no",
        "cited": "10.1016/0377-2217(95)00158-1",
        "timespan": "P1Y6M",
        "journal_sc": "no",
        "oci": "06190174478-0670226915",
        "citing": "10.1016/s0305-0548(97)00055-5"
    },
    {
        "creation": "1998-04",
        "author_sc": "no",
        "cited": "10.1287/mnsc.38.12.1803",
        "timespan": "P5Y4M",
        "journal_sc": "no",
        "oci": "06190174478-06702334301",
        "citing": "10.1016/s0305-0548(97)00055-5"
    },
    {
        "creation": "1998-04",
        "author_sc": "no",
        "cited": "10.1287/mnsc.16.5.357",
        "timespan": "P28Y3M",
        "journal_sc": "no",
        "oci": "06190174478-06702334416",
        "citing": "10.1016/s0305-0548(97)00055-5"
    },
    {
        "creation": "1998-04",
        "author_sc": "no",
        "cited": "10.1287/mnsc.17.12.b803",
        "timespan": "P26Y8M",
        "journal_sc": "no",
        "oci": "06190174478-06702334547",
        "citing": "10.1016/s0305-0548(97)00055-5"
    },
    {
        "creation": "1998-04",
        "author_sc": "no",
        "cited": "10.1137/0221065",
        "timespan": "P5Y4M",
        "journal_sc": "no",
        "oci": "06190174478-06703726811",
        "citing": "10.1016/s0305-0548(97)00055-5"
    },
    {
        "creation": "1998-04",
        "author_sc": "no",
        "cited": "10.1016/0377-2217(94)00247-9",
        "timespan": "P2Y1M",
        "journal_sc": "no",
        "oci": "06190174478-0680228049",
        "citing": "10.1016/s0305-0548(97)00055-5"
    },
    {
        "creation": "1998-04",
        "author_sc": "no",
        "cited": "10.1016/0377-2217(95)00358-4",
        "timespan": "P2Y0M",
        "journal_sc": "no",
        "oci": "06190174478-0680228336",
        "citing": "10.1016/s0305-0548(97)00055-5"
    },
    {
        "creation": "1998-04",
        "author_sc": "no",
        "cited": "10.1016/s0377-2217(96)00112-9",
        "timespan": "P0Y9M",
        "journal_sc": "no",
        "oci": "06190174478-0680228716",
        "citing": "10.1016/s0305-0548(97)00055-5"
    },
    {
        "creation": "1998-04",
        "author_sc": "no",
        "cited": "10.1287/mnsc.27.9.1040",
        "timespan": "P16Y7M",
        "journal_sc": "no",
        "oci": "06190174478-06802350734",
        "citing": "10.1016/s0305-0548(97)00055-5"
    },
    {
        "creation": "1998-04",
        "author_sc": "no",
        "cited": "10.1287/mnsc.41.10.1693",
        "timespan": "P2Y6M",
        "journal_sc": "no",
        "oci": "06190174478-06802350772",
        "citing": "10.1016/s0305-0548(97)00055-5"
    },
    {
        "creation": "1998-04",
        "author_sc": "no",
        "cited": "10.1287/mnsc.38.9.1245",
        "timespan": "P5Y7M",
        "journal_sc": "no",
        "oci": "06190174478-06802351203",
        "citing": "10.1016/s0305-0548(97)00055-5"
    },
    {
        "creation": "1998-04",
        "author_sc": "no",
        "cited": "10.1016/s0377-2217(96)00170-1",
        "timespan": "P1Y3M",
        "journal_sc": "no",
        "oci": "06190174478-0690232522",
        "citing": "10.1016/s0305-0548(97)00055-5"
    }
]