[
    {
        "author_sc": "no",
        "cited": "10.1007/978-3-540-24777-7",
        "oci": "06103018083-0618060524",
        "journal_sc": "no",
        "citing": "10.1007/978-3-319-23219-5_20",
        "creation": "2015",
        "timespan": "P11Y"
    },
    {
        "author_sc": "yes",
        "cited": "10.1109/tc.2011.203",
        "oci": "06103018083-061901342428",
        "journal_sc": "no",
        "citing": "10.1007/978-3-319-23219-5_20",
        "creation": "2015",
        "timespan": "P2Y"
    },
    {
        "author_sc": "no",
        "cited": "10.1080/095281399146607",
        "oci": "06103018083-0620772373",
        "journal_sc": "no",
        "citing": "10.1007/978-3-319-23219-5_20",
        "creation": "2015",
        "timespan": "P16Y"
    },
    {
        "author_sc": "no",
        "cited": "10.1137/s1052623499363220",
        "oci": "06103018083-062102175275",
        "journal_sc": "no",
        "citing": "10.1007/978-3-319-23219-5_20",
        "creation": "2015",
        "timespan": "P13Y"
    },
    {
        "author_sc": "no",
        "cited": "10.1007/978-1-4615-1479-4",
        "oci": "06103018083-0623067164",
        "journal_sc": "no",
        "citing": "10.1007/978-3-319-23219-5_20",
        "creation": "2015",
        "timespan": "P14Y"
    },
    {
        "author_sc": "yes",
        "cited": "10.1007/978-3-319-07046-9_15",
        "oci": "06103018083-062602674315",
        "journal_sc": "no",
        "citing": "10.1007/978-3-319-23219-5_20",
        "creation": "2015",
        "timespan": "P1Y"
    },
    {
        "author_sc": "no",
        "cited": "10.1007/s10601-006-6849-7",
        "oci": "06103018083-0690167004",
        "journal_sc": "no",
        "citing": "10.1007/978-3-319-23219-5_20",
        "creation": "2015",
        "timespan": "P9Y"
    },
    {
        "author_sc": "no",
        "cited": "10.1016/s0377-2217(96)00170-1",
        "oci": "06103018083-0690232522",
        "journal_sc": "no",
        "citing": "10.1007/978-3-319-23219-5_20",
        "creation": "2015",
        "timespan": "P18Y"
    }
]