[
    {
        "creation": "2013-03",
        "author_sc": "no",
        "cited": "10.3233/ida-2008-12102",
        "timespan": "P5Y0M",
        "journal_sc": "no",
        "oci": "0670150415-06101236893",
        "citing": "10.1016/j.patrec.2012.09.009"
    },
    {
        "creation": "2013-03",
        "author_sc": "no",
        "cited": "10.1145/361219.361224",
        "timespan": "P37Y4M",
        "journal_sc": "no",
        "oci": "0670150415-061103494670",
        "citing": "10.1016/j.patrec.2012.09.009"
    },
    {
        "creation": "2013-03",
        "author_sc": "no",
        "cited": "10.1007/978-3-642-56927-2",
        "timespan": "P12Y",
        "journal_sc": "no",
        "oci": "0670150415-0614054129",
        "citing": "10.1016/j.patrec.2012.09.009"
    },
    {
        "creation": "2013-03",
        "author_sc": "no",
        "cited": "10.1613/jair.696",
        "timespan": "P13Y0M",
        "journal_sc": "no",
        "oci": "0670150415-06170183504",
        "citing": "10.1016/j.patrec.2012.09.009"
    },
    {
        "creation": "2013-03",
        "author_sc": "no",
        "cited": "10.1016/0004-3702(95)00045-3",
        "timespan": "P17Y0M",
        "journal_sc": "no",
        "oci": "0670150415-061803104228",
        "citing": "10.1016/j.patrec.2012.09.009"
    },
    {
        "creation": "2013-03",
        "author_sc": "no",
        "cited": "10.1016/s0004-3702(83)80007-1",
        "timespan": "P30Y0M",
        "journal_sc": "no",
        "oci": "0670150415-061903115549",
        "citing": "10.1016/j.patrec.2012.09.009"
    },
    {
        "creation": "2013-03",
        "author_sc": "no",
        "cited": "10.1016/0004-3702(77)90007-8",
        "timespan": "P36Y1M",
        "journal_sc": "no",
        "oci": "0670150415-061903115661",
        "citing": "10.1016/j.patrec.2012.09.009"
    },
    {
        "creation": "2013-03",
        "author_sc": "no",
        "cited": "10.1007/0-306-48056-5_16",
        "timespan": "",
        "journal_sc": "no",
        "oci": "0670150415-061903317266",
        "citing": "10.1016/j.patrec.2012.09.009"
    },
    {
        "creation": "2013-03",
        "author_sc": "no",
        "cited": "10.1016/0004-3702(80)90051-x",
        "timespan": "P32Y5M",
        "journal_sc": "no",
        "oci": "0670150415-062103094790",
        "citing": "10.1016/j.patrec.2012.09.009"
    },
    {
        "creation": "2013-03",
        "author_sc": "no",
        "cited": "10.1016/0004-3702(92)90007-k",
        "timespan": "P20Y3M",
        "journal_sc": "no",
        "oci": "0670150415-062203099434",
        "citing": "10.1016/j.patrec.2012.09.009"
    },
    {
        "creation": "2013-03",
        "author_sc": "no",
        "cited": "10.1016/s0004-3702(02)00291-6",
        "timespan": "P10Y4M",
        "journal_sc": "no",
        "oci": "0670150415-062203099605",
        "citing": "10.1016/j.patrec.2012.09.009"
    },
    {
        "creation": "2013-03",
        "author_sc": "no",
        "cited": "10.1016/0020-0255(74)90008-5",
        "timespan": "P39Y2M",
        "journal_sc": "no",
        "oci": "0670150415-062402101695",
        "citing": "10.1016/j.patrec.2012.09.009"
    },
    {
        "creation": "2013-03",
        "author_sc": "no",
        "cited": "10.1109/ijcnn.2009.5178710",
        "timespan": "P3Y9M",
        "journal_sc": "no",
        "oci": "0670150415-062403196294",
        "citing": "10.1016/j.patrec.2012.09.009"
    },
    {
        "creation": "2013-03",
        "author_sc": "no",
        "cited": "10.1162/08997660152469369",
        "timespan": "P11Y7M",
        "journal_sc": "no",
        "oci": "0670150415-062403509559",
        "citing": "10.1016/j.patrec.2012.09.009"
    },
    {
        "creation": "2013-03",
        "author_sc": "no",
        "cited": "10.1023/a:1011402324562",
        "timespan": "P12Y",
        "journal_sc": "no",
        "oci": "0670150415-0690167082",
        "citing": "10.1016/j.patrec.2012.09.009"
    }
]