[
    {
        "author_sc": "no",
        "cited": "10.1007/978-3-540-45193-8_45",
        "oci": "061903115164-06203470696",
        "journal_sc": "no",
        "citing": "10.1016/j.artint.2011.12.001",
        "creation": "2012-05",
        "timespan": "P9Y"
    },
    {
        "author_sc": "no",
        "cited": "10.1007/978-3-540-45193-8_45",
        "oci": "062502238732-06203470696",
        "journal_sc": "no",
        "citing": "10.1007/978-3-319-66158-2_40",
        "creation": "2017",
        "timespan": "P14Y"
    },
    {
        "author_sc": "no",
        "cited": "10.1007/978-3-540-45193-8_45",
        "oci": "06303043754-06203470696",
        "journal_sc": "no",
        "citing": "10.1007/978-3-540-30201-8_20",
        "creation": "2004",
        "timespan": "P1Y"
    },
    {
        "author_sc": "no",
        "cited": "10.1007/978-3-540-45193-8_45",
        "oci": "06702451068-06203470696",
        "journal_sc": "no",
        "citing": "10.1007/978-3-030-19212-9_43",
        "creation": "2019",
        "timespan": "P16Y"
    }
]